[
  {
    "id": 1,
    "title": "TGK",
    "image_url": "https://raw.githubusercontent.com/ares-afk/banners/main/advertising/9/235х59.png",
    "target_url": "https://t.me/autobattIe",
    "position": [0, 0],
    "size": [1, 1],
    "start_date": "2025-08-16 00:00:00",
    "end_date": "2026-01-10 23:59:59"
  },
  {
    "id": 2,
    "title": "TGK",
    "image_url": "https://raw.githubusercontent.com/ares-afk/banners/main/advertising/9/235х59.png",
    "target_url": "https://t.me/autobattIe",
    "position": [1, 0],
    "size": [1, 1],
    "start_date": "2025-08-16 00:00:00",
    "end_date": "2026-01-10 23:59:59"
  },
  {
    "id": 3,
    "title": "TGK",
    "image_url": "https://raw.githubusercontent.com/ares-afk/banners/main/advertising/9/235х59.png",
    "target_url": "https://t.me/autobattIe",
    "position": [2, 0],
    "size": [1, 1],
    "start_date": "2025-08-16 00:00:00",
    "end_date": "2026-01-10 23:59:59"
  },
  {
    "id": 4,
    "title": "TGK",
    "image_url": "https://raw.githubusercontent.com/ares-afk/banners/main/advertising/9/235х59.png",
    "target_url": "https://t.me/autobattIe",
    "position": [3, 0],
    "size": [1, 1],
    "start_date": "2025-08-16 00:00:00",
    "end_date": "2026-01-10 23:59:59"
  },
  {
    "id": 5,
    "title": "TGK",
    "image_url": "https://raw.githubusercontent.com/ares-afk/banners/main/advertising/9/235х59.png",
    "target_url": "https://t.me/autobattIe",
    "position": [0, 1],
    "size": [1, 1],
    "start_date": "2025-08-16 00:00:00",
    "end_date": "2026-01-10 23:59:59"
  },
  {
    "id": 6,
    "title": "TGK",
    "image_url": "https://raw.githubusercontent.com/ares-afk/banners/main/advertising/9/235х59.png",
    "target_url": "https://t.me/autobattIe",
    "position": [1, 1],
    "size": [1, 1],
    "start_date": "2025-08-16 00:00:00",
    "end_date": "2026-01-10 23:59:59"
  },
  {
    "id": 7,
    "title": "TGK",
    "image_url": "https://raw.githubusercontent.com/ares-afk/banners/main/advertising/9/235х59.png",
    "target_url": "https://t.me/autobattIe",
    "position": [2, 1],
    "size": [1, 1],
    "start_date": "2025-08-16 00:00:00",
    "end_date": "2026-01-10 23:59:59"
  },
  {
    "id": 8,
    "title": "TGK",
    "image_url": "https://raw.githubusercontent.com/ares-afk/banners/main/advertising/9/235х59.png",
    "target_url": "https://t.me/autobattIe",
    "position": [3, 1],
    "size": [1, 1],
    "start_date": "2025-08-16 00:00:00",
    "end_date": "2026-01-10 23:59:59"
  },
  {
    "id": 9,
    "title": "TGK",
    "image_url": "https://raw.githubusercontent.com/ares-afk/banners/main/advertising/10/235x59.gif",
    "target_url": "https://t.me/autobattIe",
    "position": [0, 2],
    "size": [1, 1],
    "start_date": "2025-08-16 00:00:00",
    "end_date": "2026-01-10 23:59:59"
  }
]




















